<?xml version="1.0" encoding="UTF-8"?><?xml-stylesheet type='text/xsl' href='_UpgradeReport_Files/UpgradeReport.xslt'?><UpgradeLog>
<Properties><Property Name="Solution" Value="CES">
</Property><Property Name="Solution File" Value="E:\KASHYAP\SOFTWARES\College Examination System inst\Source Code\project Pragna Chetan Kashyap Kotak\CES\VBto VBNET\CES.sln">
</Property><Property Name="Date" Value="Friday, 25 March, 2016">
</Property><Property Name="Time" Value="0:03:12 AM">
</Property></Properties><Event ErrorLevel="0" Project="CES" Source="CES.vbproj" Description="Project file successfully backed up as E:\KASHYAP\SOFTWARES\College Examination System inst\Source Code\project Pragna Chetan Kashyap Kotak\CES\VBto VBNET\Backup\CES.vbproj">
</Event><Event ErrorLevel="0" Project="CES" Source="CES.vbproj.user" Description="Project user file successfully backed up as E:\KASHYAP\SOFTWARES\College Examination System inst\Source Code\project Pragna Chetan Kashyap Kotak\CES\VBto VBNET\Backup\CES.vbproj.user">
</Event><Event ErrorLevel="0" Project="CES" Source="AssemblyInfo.vb" Description="File successfully backed up as E:\KASHYAP\SOFTWARES\College Examination System inst\Source Code\project Pragna Chetan Kashyap Kotak\CES\VBto VBNET\Backup\AssemblyInfo.vb">
</Event><Event ErrorLevel="0" Project="CES" Source="frmBranch.vb" Description="File successfully backed up as E:\KASHYAP\SOFTWARES\College Examination System inst\Source Code\project Pragna Chetan Kashyap Kotak\CES\VBto VBNET\Backup\frmBranch.vb">
</Event><Event ErrorLevel="0" Project="CES" Source="MDIForm1.vb" Description="File successfully backed up as E:\KASHYAP\SOFTWARES\College Examination System inst\Source Code\project Pragna Chetan Kashyap Kotak\CES\VBto VBNET\Backup\MDIForm1.vb">
</Event><Event ErrorLevel="0" Project="CES" Source="Module1.vb" Description="File successfully backed up as E:\KASHYAP\SOFTWARES\College Examination System inst\Source Code\project Pragna Chetan Kashyap Kotak\CES\VBto VBNET\Backup\Module1.vb">
</Event><Event ErrorLevel="0" Project="CES" Source="frmSubjects.vb" Description="File successfully backed up as E:\KASHYAP\SOFTWARES\College Examination System inst\Source Code\project Pragna Chetan Kashyap Kotak\CES\VBto VBNET\Backup\frmSubjects.vb">
</Event><Event ErrorLevel="0" Project="CES" Source="frmLogin.vb" Description="File successfully backed up as E:\KASHYAP\SOFTWARES\College Examination System inst\Source Code\project Pragna Chetan Kashyap Kotak\CES\VBto VBNET\Backup\frmLogin.vb">
</Event><Event ErrorLevel="0" Project="CES" Source="frmSplash.vb" Description="File successfully backed up as E:\KASHYAP\SOFTWARES\College Examination System inst\Source Code\project Pragna Chetan Kashyap Kotak\CES\VBto VBNET\Backup\frmSplash.vb">
</Event><Event ErrorLevel="0" Project="CES" Source="frmAddUser.vb" Description="File successfully backed up as E:\KASHYAP\SOFTWARES\College Examination System inst\Source Code\project Pragna Chetan Kashyap Kotak\CES\VBto VBNET\Backup\frmAddUser.vb">
</Event><Event ErrorLevel="0" Project="CES" Source="frmDeleteUser.vb" Description="File successfully backed up as E:\KASHYAP\SOFTWARES\College Examination System inst\Source Code\project Pragna Chetan Kashyap Kotak\CES\VBto VBNET\Backup\frmDeleteUser.vb">
</Event><Event ErrorLevel="0" Project="CES" Source="frmChangePass.vb" Description="File successfully backed up as E:\KASHYAP\SOFTWARES\College Examination System inst\Source Code\project Pragna Chetan Kashyap Kotak\CES\VBto VBNET\Backup\frmChangePass.vb">
</Event><Event ErrorLevel="0" Project="CES" Source="frmAddQst.vb" Description="File successfully backed up as E:\KASHYAP\SOFTWARES\College Examination System inst\Source Code\project Pragna Chetan Kashyap Kotak\CES\VBto VBNET\Backup\frmAddQst.vb">
</Event><Event ErrorLevel="0" Project="CES" Source="frmStudReg.vb" Description="File successfully backed up as E:\KASHYAP\SOFTWARES\College Examination System inst\Source Code\project Pragna Chetan Kashyap Kotak\CES\VBto VBNET\Backup\frmStudReg.vb">
</Event><Event ErrorLevel="0" Project="CES" Source="frmStartExam.vb" Description="File successfully backed up as E:\KASHYAP\SOFTWARES\College Examination System inst\Source Code\project Pragna Chetan Kashyap Kotak\CES\VBto VBNET\Backup\frmStartExam.vb">
</Event><Event ErrorLevel="0" Project="CES" Source="frmSelectExam.vb" Description="File successfully backed up as E:\KASHYAP\SOFTWARES\College Examination System inst\Source Code\project Pragna Chetan Kashyap Kotak\CES\VBto VBNET\Backup\frmSelectExam.vb">
</Event><Event ErrorLevel="0" Project="CES" Source="frmViewRptQst.vb" Description="File successfully backed up as E:\KASHYAP\SOFTWARES\College Examination System inst\Source Code\project Pragna Chetan Kashyap Kotak\CES\VBto VBNET\Backup\frmViewRptQst.vb">
</Event><Event ErrorLevel="0" Project="CES" Source="frmStudRslt.vb" Description="File successfully backed up as E:\KASHYAP\SOFTWARES\College Examination System inst\Source Code\project Pragna Chetan Kashyap Kotak\CES\VBto VBNET\Backup\frmStudRslt.vb">
</Event><Event ErrorLevel="0" Project="CES" Source="Form1.vb" Description="File successfully backed up as E:\KASHYAP\SOFTWARES\College Examination System inst\Source Code\project Pragna Chetan Kashyap Kotak\CES\VBto VBNET\Backup\Form1.vb">
</Event><Event ErrorLevel="0" Project="CES" Source="frmDelSub.vb" Description="File successfully backed up as E:\KASHYAP\SOFTWARES\College Examination System inst\Source Code\project Pragna Chetan Kashyap Kotak\CES\VBto VBNET\Backup\frmDelSub.vb">
</Event><Event ErrorLevel="0" Project="CES" Source="frmDelBranch.vb" Description="File successfully backed up as E:\KASHYAP\SOFTWARES\College Examination System inst\Source Code\project Pragna Chetan Kashyap Kotak\CES\VBto VBNET\Backup\frmDelBranch.vb">
</Event><Event ErrorLevel="0" Project="CES" Source="frmAbout.vb" Description="File successfully backed up as E:\KASHYAP\SOFTWARES\College Examination System inst\Source Code\project Pragna Chetan Kashyap Kotak\CES\VBto VBNET\Backup\frmAbout.vb">
</Event><Event ErrorLevel="0" Project="CES" Source="frmSplash2.vb" Description="File successfully backed up as E:\KASHYAP\SOFTWARES\College Examination System inst\Source Code\project Pragna Chetan Kashyap Kotak\CES\VBto VBNET\Backup\frmSplash2.vb">
</Event><Event ErrorLevel="0" Project="CES" Source="frmExam.vb" Description="File successfully backed up as E:\KASHYAP\SOFTWARES\College Examination System inst\Source Code\project Pragna Chetan Kashyap Kotak\CES\VBto VBNET\Backup\frmExam.vb">
</Event><Event ErrorLevel="0" Project="CES" Source="frmTT.vb" Description="File successfully backed up as E:\KASHYAP\SOFTWARES\College Examination System inst\Source Code\project Pragna Chetan Kashyap Kotak\CES\VBto VBNET\Backup\frmTT.vb">
</Event><Event ErrorLevel="0" Project="CES" Source="frmNews.vb" Description="File successfully backed up as E:\KASHYAP\SOFTWARES\College Examination System inst\Source Code\project Pragna Chetan Kashyap Kotak\CES\VBto VBNET\Backup\frmNews.vb">
</Event><Event ErrorLevel="0" Project="CES" Source="frmFeedback.vb" Description="File successfully backed up as E:\KASHYAP\SOFTWARES\College Examination System inst\Source Code\project Pragna Chetan Kashyap Kotak\CES\VBto VBNET\Backup\frmFeedback.vb">
</Event><Event ErrorLevel="0" Project="CES" Source="frmAskdb.vb" Description="File successfully backed up as E:\KASHYAP\SOFTWARES\College Examination System inst\Source Code\project Pragna Chetan Kashyap Kotak\CES\VBto VBNET\Backup\frmAskdb.vb">
</Event><Event ErrorLevel="0" Project="CES" Source="VBto_Converter.vb" Description="File successfully backed up as E:\KASHYAP\SOFTWARES\College Examination System inst\Source Code\project Pragna Chetan Kashyap Kotak\CES\VBto VBNET\Backup\VBto_Converter.vb">
</Event><Event ErrorLevel="0" Project="CES" Source="VBto_Converter_2.vb" Description="File successfully backed up as E:\KASHYAP\SOFTWARES\College Examination System inst\Source Code\project Pragna Chetan Kashyap Kotak\CES\VBto VBNET\Backup\VBto_Converter_2.vb">
</Event><Event ErrorLevel="0" Project="CES" Source="MDIForm1_Icon.ico" Description="File successfully backed up as E:\KASHYAP\SOFTWARES\College Examination System inst\Source Code\project Pragna Chetan Kashyap Kotak\CES\VBto VBNET\Backup\MDIForm1_Icon.ico">
</Event><Event ErrorLevel="0" Project="CES" Source="frmBranch.resx" Description="File successfully backed up as E:\KASHYAP\SOFTWARES\College Examination System inst\Source Code\project Pragna Chetan Kashyap Kotak\CES\VBto VBNET\Backup\frmBranch.resx">
</Event><Event ErrorLevel="0" Project="CES" Source="MDIForm1.resx" Description="File successfully backed up as E:\KASHYAP\SOFTWARES\College Examination System inst\Source Code\project Pragna Chetan Kashyap Kotak\CES\VBto VBNET\Backup\MDIForm1.resx">
</Event><Event ErrorLevel="0" Project="CES" Source="frmSubjects.resx" Description="File successfully backed up as E:\KASHYAP\SOFTWARES\College Examination System inst\Source Code\project Pragna Chetan Kashyap Kotak\CES\VBto VBNET\Backup\frmSubjects.resx">
</Event><Event ErrorLevel="0" Project="CES" Source="frmLogin.resx" Description="File successfully backed up as E:\KASHYAP\SOFTWARES\College Examination System inst\Source Code\project Pragna Chetan Kashyap Kotak\CES\VBto VBNET\Backup\frmLogin.resx">
</Event><Event ErrorLevel="0" Project="CES" Source="frmSplash.resx" Description="File successfully backed up as E:\KASHYAP\SOFTWARES\College Examination System inst\Source Code\project Pragna Chetan Kashyap Kotak\CES\VBto VBNET\Backup\frmSplash.resx">
</Event><Event ErrorLevel="0" Project="CES" Source="frmAddUser.resx" Description="File successfully backed up as E:\KASHYAP\SOFTWARES\College Examination System inst\Source Code\project Pragna Chetan Kashyap Kotak\CES\VBto VBNET\Backup\frmAddUser.resx">
</Event><Event ErrorLevel="0" Project="CES" Source="frmDeleteUser.resx" Description="File successfully backed up as E:\KASHYAP\SOFTWARES\College Examination System inst\Source Code\project Pragna Chetan Kashyap Kotak\CES\VBto VBNET\Backup\frmDeleteUser.resx">
</Event><Event ErrorLevel="0" Project="CES" Source="frmChangePass.resx" Description="File successfully backed up as E:\KASHYAP\SOFTWARES\College Examination System inst\Source Code\project Pragna Chetan Kashyap Kotak\CES\VBto VBNET\Backup\frmChangePass.resx">
</Event><Event ErrorLevel="0" Project="CES" Source="frmAddQst.resx" Description="File successfully backed up as E:\KASHYAP\SOFTWARES\College Examination System inst\Source Code\project Pragna Chetan Kashyap Kotak\CES\VBto VBNET\Backup\frmAddQst.resx">
</Event><Event ErrorLevel="0" Project="CES" Source="frmStudReg.resx" Description="File successfully backed up as E:\KASHYAP\SOFTWARES\College Examination System inst\Source Code\project Pragna Chetan Kashyap Kotak\CES\VBto VBNET\Backup\frmStudReg.resx">
</Event><Event ErrorLevel="0" Project="CES" Source="frmStartExam.resx" Description="File successfully backed up as E:\KASHYAP\SOFTWARES\College Examination System inst\Source Code\project Pragna Chetan Kashyap Kotak\CES\VBto VBNET\Backup\frmStartExam.resx">
</Event><Event ErrorLevel="0" Project="CES" Source="frmSelectExam.resx" Description="File successfully backed up as E:\KASHYAP\SOFTWARES\College Examination System inst\Source Code\project Pragna Chetan Kashyap Kotak\CES\VBto VBNET\Backup\frmSelectExam.resx">
</Event><Event ErrorLevel="0" Project="CES" Source="frmViewRptQst.resx" Description="File successfully backed up as E:\KASHYAP\SOFTWARES\College Examination System inst\Source Code\project Pragna Chetan Kashyap Kotak\CES\VBto VBNET\Backup\frmViewRptQst.resx">
</Event><Event ErrorLevel="0" Project="CES" Source="frmStudRslt.resx" Description="File successfully backed up as E:\KASHYAP\SOFTWARES\College Examination System inst\Source Code\project Pragna Chetan Kashyap Kotak\CES\VBto VBNET\Backup\frmStudRslt.resx">
</Event><Event ErrorLevel="0" Project="CES" Source="Form1.resx" Description="File successfully backed up as E:\KASHYAP\SOFTWARES\College Examination System inst\Source Code\project Pragna Chetan Kashyap Kotak\CES\VBto VBNET\Backup\Form1.resx">
</Event><Event ErrorLevel="0" Project="CES" Source="frmDelSub.resx" Description="File successfully backed up as E:\KASHYAP\SOFTWARES\College Examination System inst\Source Code\project Pragna Chetan Kashyap Kotak\CES\VBto VBNET\Backup\frmDelSub.resx">
</Event><Event ErrorLevel="0" Project="CES" Source="frmDelBranch.resx" Description="File successfully backed up as E:\KASHYAP\SOFTWARES\College Examination System inst\Source Code\project Pragna Chetan Kashyap Kotak\CES\VBto VBNET\Backup\frmDelBranch.resx">
</Event><Event ErrorLevel="0" Project="CES" Source="frmAbout.resx" Description="File successfully backed up as E:\KASHYAP\SOFTWARES\College Examination System inst\Source Code\project Pragna Chetan Kashyap Kotak\CES\VBto VBNET\Backup\frmAbout.resx">
</Event><Event ErrorLevel="0" Project="CES" Source="frmSplash2.resx" Description="File successfully backed up as E:\KASHYAP\SOFTWARES\College Examination System inst\Source Code\project Pragna Chetan Kashyap Kotak\CES\VBto VBNET\Backup\frmSplash2.resx">
</Event><Event ErrorLevel="0" Project="CES" Source="frmExam.resx" Description="File successfully backed up as E:\KASHYAP\SOFTWARES\College Examination System inst\Source Code\project Pragna Chetan Kashyap Kotak\CES\VBto VBNET\Backup\frmExam.resx">
</Event><Event ErrorLevel="0" Project="CES" Source="frmTT.resx" Description="File successfully backed up as E:\KASHYAP\SOFTWARES\College Examination System inst\Source Code\project Pragna Chetan Kashyap Kotak\CES\VBto VBNET\Backup\frmTT.resx">
</Event><Event ErrorLevel="0" Project="CES" Source="frmNews.resx" Description="File successfully backed up as E:\KASHYAP\SOFTWARES\College Examination System inst\Source Code\project Pragna Chetan Kashyap Kotak\CES\VBto VBNET\Backup\frmNews.resx">
</Event><Event ErrorLevel="0" Project="CES" Source="frmFeedback.resx" Description="File successfully backed up as E:\KASHYAP\SOFTWARES\College Examination System inst\Source Code\project Pragna Chetan Kashyap Kotak\CES\VBto VBNET\Backup\frmFeedback.resx">
</Event><Event ErrorLevel="0" Project="CES" Source="frmAskdb.resx" Description="File successfully backed up as E:\KASHYAP\SOFTWARES\College Examination System inst\Source Code\project Pragna Chetan Kashyap Kotak\CES\VBto VBNET\Backup\frmAskdb.resx">
</Event><Event ErrorLevel="0" Project="CES" Source="CES.vbproj" Description="Project converted successfully">
</Event><Event ErrorLevel="3" Project="CES" Source="CES.vbproj" Description="Converted">
</Event><Event ErrorLevel="0" Project="CES" Source="CES.vbproj" Description="Scan complete: Upgrade not required for project files.">
</Event></UpgradeLog>